AnimeCrawler/__init__.py
AnimeCrawler/__main__.py
AnimeCrawler/base_spider.py
AnimeCrawler/log.py
AnimeCrawler/cli/__init__.py
AnimeCrawler/cli/run.py
AnimeCrawler/mhyyy/__init__.py
AnimeCrawler/mhyyy/downloader.py
AnimeCrawler/mhyyy/searcher.py
AnimeCrawler/mhyyy/spider.py
AnimeCrawler/utils/__init__.py
AnimeCrawler/utils/decode.py
AnimeCrawler/utils/file.py
AnimeCrawler-0.2.1.dist-info/LICENSE
AnimeCrawler-0.2.1.dist-info/METADATA
AnimeCrawler-0.2.1.dist-info/WHEEL
AnimeCrawler-0.2.1.dist-info/entry_points.txt
AnimeCrawler-0.2.1.dist-info/top_level.txt
AnimeCrawler-0.2.1.dist-info/RECORD
