Metadata-Version: 2.1
Name: AnimeCrawler
Version: 0.2.1
Summary: 一个可免费下载动漫的爬虫
Home-page: https://github.com/Senvlin/AnimeCrawler
Author: Senvlin
Author-email: 2994515402@qq.com
Classifier: Programming Language :: Python :: 3
Classifier: License :: OSI Approved :: MIT License
Classifier: Operating System :: OS Independent
Requires-Python: >=3.8
License-File: LICENSE
Requires-Dist: ruia
Requires-Dist: tqdm
Requires-Dist: aiofiles
Requires-Dist: wheel
